[
    {
        "Author": "TooTired",
        "Name": "Go to place",
        "Punchline": "Punchline, just testing rn",
        "Description": "Description, testing rn",
        "Changelog": "",
        "InternalName": "SamplePlugin",
        "AssemblyVersion": "0.0.1",
        "RepoUrl": "https://www.youtube.com/watch?v=dQw4w9WgXcQ",
        "ApplicableVersion": "any",
        "CategoryTags": [
            "utility"
        ],
        "DalamudApiLevel": 9,
        "IconUrl": "",
        "ImageUrls": [
            ""
        ],
        "DownloadLinkInstall": "https://github.com/InstituteOfCeruleumEnergy/DalamudCustomPluginRepo/releases/download/0.0.1/go.zip",
        "IsHide": false,
        "IsTestingExclusive": false,
        "DownloadLinkTesting": "https://github.com/InstituteOfCeruleumEnergy/DalamudCustomPluginRepo/releases/download/0.0.1/go.zip",
        "DownloadLinkUpdate": "https://github.com/InstituteOfCeruleumEnergy/DalamudCustomPluginRepo/releases/download/0.0.1/go.zip",
        "DownloadCount": 0,
        "LastUpdate": "1696379002"
    }
]
